ef_image_processing/__init__.py
ef_image_processing/ef_processing/__init__.py
ef_image_processing/ef_processing/combination.py
ef_image_processing/ef_processing/transformation.py
ef_image_processing/utils/__init__.py
ef_image_processing/utils/io.py
ef_image_processing/utils/plot.py
ef_image_processing-0.0.1.dist-info/METADATA
ef_image_processing-0.0.1.dist-info/WHEEL
ef_image_processing-0.0.1.dist-info/top_level.txt
ef_image_processing-0.0.1.dist-info/RECORD
