Metadata-Version: 2.1
Name: ef-image-processing
Version: 0.0.1
Summary: Color change from original project image to reference image color
Home-page: https://github.com/eferreira50/dio-desafio-github-primeiro-repositorio/Desafio-de-Projeto/image-processing-package
Author: Elpidio
Author-email: eferreira1@gmail.com
Requires-Python: >=3.9
Requires-Dist: matplotlib
Requires-Dist: numpy
Requires-Dist: scikit-image (>=0.16.1)
